LICENSE
MANIFEST.in
README.md
setup.py
flask_utils/__init__.py
flask_utils/decorators.py
flask_utils/jinja2htmlcompress.py
flask_utils.egg-info/PKG-INFO
flask_utils.egg-info/SOURCES.txt
flask_utils.egg-info/dependency_links.txt
flask_utils.egg-info/not-zip-safe
flask_utils.egg-info/requires.txt
flask_utils.egg-info/top_level.txt