Metadata-Version: 1.1
Name: flask-utils
Version: 0.1.0
Summary: Various Flask utilities.
Home-page: https://bitbucket.org/zalew/flask-utils
Author: Jakub Zalewski
Author-email: zalew7@gmail.com
License: MIT license
Keywords: flask utils
Platform: UNKNOWN
Classifier: Development Status :: 5 - Production/Stable
Classifier: Environment :: Web Environment
Classifier: Intended Audience :: Developers
Classifier: License :: OSI Approved :: MIT License
Classifier: Operating System :: OS Independent
Classifier: Programming Language :: Python
Classifier: Programming Language :: Python :: 2
Classifier: Framework :: Flask
